experiments/E05_tiny_core_scan/src/tiny_core_scan.v

`timescale 1ns/1ps

module tiny_core_scan (
    input  wire clk,
    input  wire rst_n,

    // Functional inputs
    input  wire in_a,
    input  wire in_b,
    input  wire in_c,

    // Scan signals
    input  wire scan_en,
    input  wire scan_in,
    output wire scan_out,

    // Functional output
    output wire y
);

    reg [3:0] q;

    wire d0;
    wire d1;
    wire d2;
    wire d3;

    // ============================================
    // Functional combinational logic
    // ============================================

    assign d0 = in_a ^ q[3];
    assign d1 = q[0] & in_b;
    assign d2 = q[1] ^ q[0];
    assign d3 = q[2] | in_c;

    // ============================================
    // Scan / functional storage
    // ============================================

    always @(posedge clk or negedge rst_n) begin
        if (!rst_n) begin
            q <= 4'b0000;
        end
        else if (scan_en) begin

            // Shift mode
            q[0] <= scan_in;
            q[1] <= q[0];
            q[2] <= q[1];
            q[3] <= q[2];

        end
        else begin

            // Functional / capture mode
            q[0] <= d0;
            q[1] <= d1;
            q[2] <= d2;
            q[3] <= d3;

        end
    end

    assign scan_out = q[3];

    assign y = q[3] ^ q[1];

endmodule

experiments/E05_tiny_core_scan/tb/tiny_core_scan_tb.v
`timescale 1ns/1ps

module tiny_core_scan_tb;

    reg clk;
    reg rst_n;

    reg in_a;
    reg in_b;
    reg in_c;

    reg scan_en;
    reg scan_in;

    wire scan_out;
    wire y;

    integer errors;

    tiny_core_scan dut (
        .clk(clk),
        .rst_n(rst_n),

        .in_a(in_a),
        .in_b(in_b),
        .in_c(in_c),

        .scan_en(scan_en),
        .scan_in(scan_in),
        .scan_out(scan_out),

        .y(y)
    );

    // 10 ns clock period
    initial begin
        clk = 0;
        forever #5 clk = ~clk;
    end

    // --------------------------------------------
    // Shift one bit into the scan chain
    // --------------------------------------------
    task shift_in_bit;
        input bit_value;
        begin
            @(negedge clk);
            scan_in = bit_value;

            @(posedge clk);
            #1;

            $display(
                "[SHIFT-IN] SI=%b  q=%b",
                bit_value,
                dut.q
            );
        end
    endtask

    // --------------------------------------------
    // Check one scan-out bit, then shift once
    // --------------------------------------------
    task check_shift_out;
        input expected_bit;
        begin
            @(negedge clk);

            if (scan_out !== expected_bit) begin
                $display(
                    "[FAIL] scan_out expected=%b actual=%b",
                    expected_bit,
                    scan_out
                );
                errors = errors + 1;
            end
            else begin
                $display(
                    "[PASS] scan_out=%b",
                    scan_out
                );
            end

            scan_in = 1'b0;

            @(posedge clk);
            #1;
        end
    endtask

    // --------------------------------------------
    // Run one functional cycle (scan_en = 0).
    // y is checked at negedge (combinational from current q);
    // q is checked after the posedge capture.
    // --------------------------------------------
    task func_cycle;
        input fa;
        input fb;
        input fc;
        input [3:0] exp_q;
        input exp_y;
        begin
            @(negedge clk);
            in_a = fa;
            in_b = fb;
            in_c = fc;

            if (y !== exp_y) begin
                $display(
                    "[FAIL] func y expected=%b actual=%b (q=%b)",
                    exp_y, y, dut.q
                );
                errors = errors + 1;
            end

            @(posedge clk);
            #1;

            $display(
                "[FUNC] t=%0t  in=%b%b%b  q=%b (expect %b)",
                $time, fa, fb, fc, dut.q, exp_q
            );
            if (dut.q !== exp_q) begin
                $display(
                    "[FAIL] func q expected=%b actual=%b",
                    exp_q, dut.q
                );
                errors = errors + 1;
            end
        end
    endtask

    initial begin

        $dumpfile("waves/wave.vcd");
        $dumpvars(0, tiny_core_scan_tb);

        errors = 0;

        rst_n   = 0;
        in_a    = 0;
        in_b    = 0;
        in_c    = 0;
        scan_en = 0;
        scan_in = 0;

        // ========================================
        // 1. RESET
        // ========================================

        #12;
        rst_n = 1;

        $display("");
        $display("========== RESET DONE ==========");

        // ========================================
        // 2. FUNCTIONAL MODE (scan_en = 0)
        // ========================================

        scan_en = 0;

        $display("");
        $display("========== FUNCTIONAL (scan_en=0) ==========");

        // q=0000: d=1001, y=0
        func_cycle(1'b1, 1'b0, 1'b1, 4'b1001, 1'b0);
        // q=1001: d=0111, y=1
        func_cycle(1'b0, 1'b1, 1'b0, 4'b0111, 1'b1);
        // q=0111: d=1011, y=1
        func_cycle(1'b1, 1'b1, 1'b1, 4'b1011, 1'b1);
        // q=1011: d=0001, y=0
        func_cycle(1'b0, 1'b0, 1'b0, 4'b0001, 1'b0);

        // ========================================
        // 3. SHIFT-IN 1010
        // ========================================

        scan_en = 1;

        shift_in_bit(1);
        shift_in_bit(0);
        shift_in_bit(1);
        shift_in_bit(0);

        if (dut.q !== 4'b1010) begin
            $display(
                "[FAIL] Shift-In expected q=1010 actual=%b",
                dut.q
            );
            errors = errors + 1;
        end
        else begin
            $display(
                "[PASS] Shift-In loaded q=1010"
            );
        end

        // ========================================
        // 4. CAPTURE
        // ========================================

        @(negedge clk);

        scan_en = 0;

        in_a = 1;
        in_b = 1;
        in_c = 0;

        @(posedge clk);
        #1;

        $display("");
        $display("========== CAPTURE ==========");
        $display("Captured q = %b", dut.q);

        if (dut.q !== 4'b0100) begin
            $display(
                "[FAIL] Capture expected q=0100 actual=%b",
                dut.q
            );
            errors = errors + 1;
        end
        else begin
            $display(
                "[PASS] Capture result q=0100"
            );
        end

        // ========================================
        // 5. SHIFT-OUT 0100
        // ========================================

        scan_en = 1;

        $display("");
        $display("========== SHIFT-OUT ==========");

        // q = 0100
        // scan_out = q[3]
        // expected serial order:
        // 0 -> 1 -> 0 -> 0

        check_shift_out(0);
        check_shift_out(1);
        check_shift_out(0);
        check_shift_out(0);

        // ========================================
        // 6. BACK TO FUNCTIONAL (q should be 0000)
        // ========================================

        scan_en = 0;

        $display("");
        $display("========== BACK TO FUNCTIONAL ==========");

        if (dut.q !== 4'b0000) begin
            $display(
                "[FAIL] after shift-out q expected=0000 actual=%b",
                dut.q
            );
            errors = errors + 1;
        end
        else begin
            $display("[PASS] chain empty, q=0000");
        end

        // q=0000: d=0001, y=0
        func_cycle(1'b1, 1'b1, 1'b0, 4'b0001, 1'b0);

        // ========================================
        // FINAL RESULT
        // ========================================

        $display("");

        if (errors == 0)
            $display("========== E05 PASS ==========");
        else
            $display(
                "========== E05 FAIL: %0d errors ==========",
                errors
            );

        #10;
        $finish;

    end

endmodule

experiments/E05_tiny_core_scan/waves/wave.vcd
$date
	Sat Sep 05 03:14:02 2026
$end
$version
	Icarus Verilog
$end
$timescale
	1ps
$end
$scope module tiny_core_scan_tb $end
$var wire 1 ! y $end
$var wire 1 " scan_out $end
$var reg 1 # clk $end
$var reg 1 $ in_a $end
$var reg 1 % in_b $end
$var reg 1 & in_c $end
$var reg 1 ' rst_n $end
$var reg 1 ( scan_en $end
$var reg 1 ) scan_in $end
$var integer 32 * errors [31:0] $end
$scope module dut $end
$var wire 1 # clk $end
$var wire 1 + d0 $end
$var wire 1 , d1 $end
$var wire 1 - d2 $end
$var wire 1 . d3 $end
$var wire 1 $ in_a $end
$var wire 1 % in_b $end
$var wire 1 & in_c $end
$var wire 1 ' rst_n $end
$var wire 1 ( scan_en $end
$var wire 1 ) scan_in $end
$var wire 1 ! y $end
$var wire 1 " scan_out $end
$var reg 4 / q [3:0] $end
$upscope $end
$scope task check_shift_out $end
$var reg 1 0 expected_bit $end
$upscope $end
$scope task func_cycle $end
$var reg 4 1 exp_q [3:0] $end
$var reg 1 2 exp_y $end
$var reg 1 3 fa $end
$var reg 1 4 fb $end
$var reg 1 5 fc $end
$upscope $end
$scope task shift_in_bit $end
$var reg 1 6 bit_value $end
$upscope $end
$upscope $end
$enddefinitions $end
$comment Show the parameter values. $end
$dumpall
$end
#0
$dumpvars
x6
x5
x4
x3
x2
bx 1
x0
b0 /
0.
0-
0,
0+
b0 *
0)
0(
0'
0&
0%
0$
0#
0"
0!
$end
#5000
1#
#10000
0#
#12000
02
b1001 1
15
04
13
1'
#15000
1#
#20000
1.
1+
1&
1$
0#
#25000
0+
1!
1-
1"
b1001 /
1#
#26000
12
b111 1
05
14
03
#30000
0.
1,
1+
0&
1%
0$
0#
#35000
0+
1.
0-
0"
b111 /
1#
#36000
b1011 1
15
13
#40000
1+
1&
1$
0#
#45000
0+
0!
1"
b1011 /
1#
#46000
02
b1 1
05
04
03
#50000
0.
0,
1+
0&
0%
0$
0#
#55000
0+
1-
0"
b1 /
1#
#56000
16
1(
#60000
1)
0#
#65000
0-
1!
b11 /
1#
#66000
06
#70000
0)
0#
#75000
1.
1-
b110 /
1#
#76000
16
#80000
1)
0#
#85000
1+
1"
b1101 /
1#
#86000
06
#90000
0)
0#
#95000
0.
0!
b1010 /
1#
#100000
0+
1%
1$
0(
0#
#105000
1+
1.
0-
0"
b100 /
1#
#106000
00
1(
#110000
0#
#115000
0+
1!
0.
1"
b1000 /
1#
#116000
10
#120000
0#
#125000
1+
0!
0"
b0 /
1#
#126000
00
#130000
0#
#135000
1#
#140000
0#
#145000
1#
#146000
14
13
0(
#150000
0#
#155000
1,
1-
b1 /
1#
#160000
0#
#165000
1.
0-
1!
b111 /
1#
